{"skeleton":{"hash":"iJxOT9HaXlBtacp6nLS0DK7U9Do","spine":"3.8.99","x":-52.36,"y":-85.78,"width":147.78,"height":157.09,"images":"","audio":""},"bones":[{"name":"root"},{"name":"zong","parent":"root","x":-1.17,"y":-74.84},{"name":"zhongxin","parent":"zong","x":3.84,"y":69.95,"scaleX":0.7702,"scaleY":0.7702},{"name":"majiang","parent":"zhongxin","length":68.8,"rotation":104.77,"x":-9.46,"y":-66.55},{"name":"eyes","parent":"majiang","rotation":-104.77,"x":102,"y":-24.07},{"name":"tear1","parent":"eyes","length":26.5,"rotation":172.69,"x":-7.09,"y":4.25},{"name":"eyes2","parent":"majiang","rotation":-81.6,"x":101.69,"y":-46.49,"scaleX":-1},{"name":"mouth","parent":"majiang","rotation":-104.77,"x":61.35,"y":-37.53},{"name":"tear2","parent":"eyes2","length":26.5,"rotation":158.89,"x":-8.72,"y":4.45,"scaleX":0.9044,"scaleY":0.9044},{"name":"wotainanle","parent":"zhongxin","x":44.32,"y":-40.4},{"name":"wo1","parent":"wotainanle","x":-73.26,"y":-58.41},{"name":"le1","parent":"wotainanle","x":64.9,"y":-9.89},{"name":"nan1","parent":"wotainanle","x":25.8,"y":-19.66},{"name":"tai1","parent":"wotainanle","x":-21.78,"y":-35.16},{"name":"nanN","parent":"majiang","x":74.39,"y":-37.36}],"slots":[{"name":"majiang","bone":"majiang","attachment":"majiang"},{"name":"eyes","bone":"eyes","attachment":"eyes"},{"name":"eyes2","bone":"eyes2","attachment":"eyes"},{"name":"tear1","bone":"tear1","color":"8be1f6d4","attachment":"tear4"},{"name":"tear2","bone":"tear2","color":"8be1f6d4","attachment":"tear4"},{"name":"mouth","bone":"mouth","attachment":"mouth"},{"name":"le1","bone":"le1","attachment":"le1"},{"name":"nan1","bone":"nan1","attachment":"nan1"},{"name":"tai1","bone":"tai1","attachment":"tai1"},{"name":"wo1","bone":"wo1","attachment":"wo1"},{"name":"nanN","bone":"nanN","attachment":"nanN"}],"skins":[{"name":"default","attachments":{"eyes":{"eyes":{"x":-7.75,"y":3.66,"width":25,"height":14}},"eyes2":{"eyes":{"x":-7.75,"y":3.66,"width":25,"height":14}},"le1":{"le1":{"x":-3.8,"y":26.51,"width":30,"height":53}},"majiang":{"majiang":{"x":69.98,"y":-22.6,"rotation":-104.77,"width":132,"height":152}},"mouth":{"mouth":{"x":3.37,"y":-5.47,"width":56,"height":42}},"nan1":{"nan1":{"x":-2.7,"y":25.23,"width":40,"height":64}},"nanN":{"nanN":{"x":-0.33,"y":-8.99,"rotation":-104.77,"width":68,"height":77}},"tai1":{"tai1":{"x":-1.01,"y":28.36,"width":52,"height":71}},"tear1":{"tear1":{"x":24.4,"y":10.05,"rotation":-172.69,"width":58,"height":70},"tear2":{"x":23.85,"y":6.46,"rotation":-172.69,"width":56,"height":67},"tear3":{"x":25.09,"y":8.63,"rotation":-172.69,"width":61,"height":69},"tear4":{"x":22.54,"y":8.81,"rotation":-172.69,"width":54,"height":68}},"tear2":{"tear1":{"x":24.4,"y":10.05,"rotation":-172.69,"width":58,"height":70},"tear2":{"x":23.85,"y":6.46,"rotation":-172.69,"width":56,"height":67},"tear3":{"x":25.09,"y":8.63,"rotation":-172.69,"width":61,"height":69},"tear4":{"x":22.54,"y":8.81,"rotation":-172.69,"width":54,"height":68}},"wo1":{"wo1":{"x":-6.5,"y":33.78,"width":68,"height":80}}}}],"animations":{"default":{"slots":{"eyes":{"color":[{"time":1.1667,"color":"ffffffff"},{"time":1.2667,"color":"ffffff00"}]},"eyes2":{"color":[{"time":1.1667,"color":"ffffffff"},{"time":1.2667,"color":"ffffff00"}]},"le1":{"color":[{"color":"ffffff00","curve":"stepped"},{"time":0.2333,"color":"ffffff00"},{"time":0.3,"color":"ffffffff","curve":"stepped"},{"time":0.5667,"color":"ffffffff","curve":"stepped"},{"time":1.2667,"color":"ffffffff"},{"time":1.3333,"color":"ffffff00"}]},"majiang":{"color":[{"time":1.3667,"color":"ffffffff","curve":"stepped"},{"time":1.4667,"color":"ffffffff"}]},"mouth":{"color":[{"time":1.1667,"color":"ffffffff"},{"time":1.2667,"color":"ffffff00"}]},"nan1":{"color":[{"color":"ffffff00","curve":"stepped"},{"time":0.2,"color":"ffffff00"},{"time":0.2667,"color":"ffffffff","curve":"stepped"},{"time":0.3667,"color":"ffffffff","curve":"stepped"},{"time":0.4333,"color":"ffffffff","curve":"stepped"},{"time":0.6333,"color":"ffffffff","curve":"stepped"},{"time":1.2667,"color":"ffffffff"},{"time":1.3333,"color":"ffffff00"}]},"nanN":{"color":[{"color":"ffffff00","curve":"stepped"},{"time":1.2667,"color":"ffffff00"},{"time":1.4667,"color":"ffffffff","curve":"stepped"},{"time":2,"color":"ffffffff"}]},"tai1":{"color":[{"color":"ffffff00","curve":"stepped"},{"time":0.1333,"color":"ffffff00"},{"time":0.2,"color":"ffffffff","curve":"stepped"},{"time":0.2667,"color":"ffffffff","curve":"stepped"},{"time":0.3333,"color":"ffffffff","curve":"stepped"},{"time":0.4333,"color":"ffffffff","curve":"stepped"},{"time":1.2667,"color":"ffffffff"},{"time":1.3333,"color":"ffffff00"}]},"tear1":{"color":[{"time":1.1667,"color":"8be1f6d4"},{"time":1.2667,"color":"8be0f600"}],"attachment":[{"name":null},{"time":0.0667,"name":"tear1"},{"time":0.1333,"name":"tear2"},{"time":0.2,"name":"tear3"},{"time":0.2667,"name":"tear4"},{"time":0.3333,"name":"tear1"},{"time":0.4,"name":"tear2"},{"time":0.4667,"name":"tear3"},{"time":0.5333,"name":"tear4"},{"time":0.6,"name":"tear1"},{"time":0.6667,"name":"tear2"},{"time":0.7333,"name":"tear3"},{"time":0.8,"name":"tear4"},{"time":0.8667,"name":"tear1"},{"time":0.9333,"name":"tear2"},{"time":1,"name":"tear3"},{"time":1.0667,"name":"tear4"},{"time":1.1333,"name":"tear1"},{"time":1.2,"name":"tear2"},{"time":1.2667,"name":"tear3"},{"time":1.3333,"name":"tear4"},{"time":1.4,"name":"tear1"},{"time":1.4667,"name":"tear2"}]},"tear2":{"color":[{"time":1.1667,"color":"8be1f6d4"},{"time":1.2667,"color":"8be0f600"}],"attachment":[{"name":null},{"time":0.0667,"name":"tear2"},{"time":0.1333,"name":"tear3"},{"time":0.2,"name":"tear4"},{"time":0.2667,"name":"tear1"},{"time":0.3333,"name":"tear2"},{"time":0.4,"name":"tear3"},{"time":0.4667,"name":"tear4"},{"time":0.5333,"name":"tear1"},{"time":0.6,"name":"tear2"},{"time":0.6667,"name":"tear3"},{"time":0.7333,"name":"tear4"},{"time":0.8,"name":"tear1"},{"time":0.8667,"name":"tear2"},{"time":0.9333,"name":"tear3"},{"time":1,"name":"tear4"},{"time":1.0667,"name":"tear1"},{"time":1.1333,"name":"tear2"},{"time":1.2,"name":"tear3"},{"time":1.2667,"name":"tear4"},{"time":1.3333,"name":"tear1"},{"time":1.4,"name":"tear2"},{"time":1.4667,"name":"tear3"}]},"wo1":{"color":[{"color":"ffffff00"},{"time":0.0667,"color":"ffffffff","curve":"stepped"},{"time":1.2667,"color":"ffffffff"},{"time":1.3333,"color":"ffffff00"}]}},"bones":{"eyes":{"rotate":[{}],"translate":[{}],"scale":[{}],"shear":[{}]},"eyes2":{"rotate":[{}],"translate":[{}],"scale":[{}],"shear":[{}]},"le1":{"rotate":[{"curve":"stepped"},{"time":0.2333,"curve":"stepped"},{"time":0.4,"curve":"stepped"},{"time":0.4667,"curve":"stepped"},{"time":0.5667}],"translate":[{"y":147.34,"curve":"stepped"},{"time":0.2333,"y":147.34},{"time":0.4,"curve":"stepped"},{"time":0.4667,"curve":"stepped"},{"time":0.5667}],"scale":[{"curve":"stepped"},{"time":0.2333,"curve":"stepped"},{"time":0.4},{"time":0.4667,"y":0.712},{"time":0.5667}],"shear":[{"curve":"stepped"},{"time":0.2333,"curve":"stepped"},{"time":0.4,"curve":"stepped"},{"time":0.4667,"curve":"stepped"},{"time":0.5667}]},"majiang":{"rotate":[{}],"translate":[{}],"scale":[{"curve":0.25,"c3":0.75},{"time":0.2,"x":1.074,"curve":0.25,"c3":0.75},{"time":0.4,"curve":0.25,"c3":0.75},{"time":0.6,"x":1.074,"curve":0.25,"c3":0.75},{"time":0.8,"curve":0.25,"c3":0.75},{"time":1,"x":1.074,"curve":0.25,"c3":0.75},{"time":1.2,"curve":0.25,"c3":0.75},{"time":1.3333,"x":1.179},{"time":1.5}],"shear":[{}]},"mouth":{"rotate":[{}],"translate":[{}],"scale":[{"x":0.766,"y":0.766},{"time":0.2333},{"time":0.4667,"x":0.766,"y":0.766},{"time":0.7},{"time":0.9333,"x":0.766,"y":0.766},{"time":1.1667},{"time":1.4,"x":0.766,"y":0.766}],"shear":[{}]},"nan1":{"rotate":[{"curve":"stepped"},{"time":0.2,"curve":"stepped"},{"time":0.3667,"curve":"stepped"},{"time":0.4333,"curve":"stepped"},{"time":0.6333}],"translate":[{"y":155.48,"curve":"stepped"},{"time":0.2,"y":155.48},{"time":0.3667,"curve":"stepped"},{"time":0.4333,"curve":"stepped"},{"time":0.6333}],"scale":[{"curve":"stepped"},{"time":0.2,"curve":"stepped"},{"time":0.3667},{"time":0.4333,"y":0.594},{"time":0.6333,"y":1.187},{"time":0.7}],"shear":[{"curve":"stepped"},{"time":0.2,"curve":"stepped"},{"time":0.3667,"curve":"stepped"},{"time":0.4333,"curve":"stepped"},{"time":0.6333}]},"nanN":{"rotate":[{"curve":"stepped"},{"time":1.2667,"curve":"stepped"},{"time":2}],"translate":[{"curve":"stepped"},{"time":1.2667,"curve":"stepped"},{"time":1.3667,"curve":"stepped"},{"time":2}],"scale":[{"curve":"stepped"},{"time":1.2667,"curve":"stepped"},{"time":2}],"shear":[{"curve":"stepped"},{"time":1.2667,"curve":"stepped"},{"time":2}]},"tai1":{"rotate":[{"curve":"stepped"},{"time":0.1333,"curve":"stepped"},{"time":0.2667,"curve":"stepped"},{"time":0.3333,"curve":"stepped"},{"time":0.4333}],"translate":[{"y":189.45,"curve":"stepped"},{"time":0.1333,"y":189.45},{"time":0.2667,"curve":"stepped"},{"time":0.3333,"curve":"stepped"},{"time":0.4333}],"scale":[{"curve":"stepped"},{"time":0.1333,"curve":"stepped"},{"time":0.2667},{"time":0.3333,"y":0.726},{"time":0.4333}],"shear":[{"curve":"stepped"},{"time":0.1333,"curve":"stepped"},{"time":0.2667,"curve":"stepped"},{"time":0.3333,"curve":"stepped"},{"time":0.4333}]},"tear1":{"rotate":[{}],"translate":[{}],"scale":[{}],"shear":[{}]},"tear2":{"rotate":[{}],"translate":[{}],"scale":[{}],"shear":[{}]},"wo1":{"rotate":[{"curve":"stepped"},{"time":0.2,"curve":"stepped"},{"time":0.2667,"curve":"stepped"},{"time":0.3667}],"translate":[{"y":197.24},{"time":0.2,"curve":"stepped"},{"time":0.2667,"curve":"stepped"},{"time":0.3667}],"scale":[{"curve":"stepped"},{"time":0.2},{"time":0.2667,"y":0.829},{"time":0.3667}],"shear":[{"curve":"stepped"},{"time":0.2,"curve":"stepped"},{"time":0.2667,"curve":"stepped"},{"time":0.3667}]},"root":{"rotate":[{}],"translate":[{}],"scale":[{}],"shear":[{}]},"zhongxin":{"rotate":[{}],"translate":[{}],"scale":[{}],"shear":[{}]},"zong":{"rotate":[{}],"translate":[{}],"scale":[{}],"shear":[{}]},"wotainanle":{"rotate":[{"curve":"stepped"},{"time":1.1333}],"translate":[{"curve":"stepped"},{"time":1.1333},{"time":1.2667,"y":-96.06}],"scale":[{"curve":"stepped"},{"time":1.1333}],"shear":[{"curve":"stepped"},{"time":1.1333}]}}}}}