[
    {
        "cn": "登录",
        "tw": "登錄",
        "en": "Login"
    },
    {
        "cn": "当前网络 {%0}",
        "tw": "當前網絡 {%0}",
        "en": "Network {%0}"
    },
    {
        "cn": "当前地址 {%0}",
        "tw": "當前地址 {%0}",
        "en": "Address {%0}"
    },
    {
        "cn": "加载中",
        "tw": "加載中",
        "en": "Loading"
    },
    {
        "cn": "返回",
        "tw": "返回",
        "en": "Return"
    },
    {
        "cn": "正在加载资源 {%0}",
        "tw": "正在加載資源 {%0}",
        "en": "Loading resources {%0}"
    },
    {
        "cn": "邀请",
        "tw": "邀請",
        "en": "Invite"
    },
    {
        "cn": "快速开始",
        "tw": "快速開始",
        "en": "Quick Start"
    },
    {
        "cn": "快速开始",
        "tw": "快速開始",
        "en": "Quick Start"
    },
    {
        "cn": "房间数量",
        "tw": "房間數量",
        "en": "Room Count"
    },
    {
        "cn": "加入",
        "tw": "加入",
        "en": "Join"
    },
    {
        "cn": "在线",
        "tw": "在線",
        "en": "Online"
    },
    {
        "cn": "俱乐部",
        "tw": "俱樂部",
        "en": "Club"
    },
    {
        "cn": "职业生涯数据",
        "tw": "職業生涯數據",
        "en": "Career Data"
    },
    {
        "cn": "收到的礼物",
        "tw": "收到的禮物",
        "en": "Received Gifts"
    },
    {
        "cn": "德州扑克",
        "tw": "德州撲克",
        "en": "Texas Hold'em"
    },
    {
        "cn": "牛牛",
        "tw": "牛牛",
        "en": "Niu Niu"
    },
    {
        "cn": "斗地主",
        "tw": "鬥地主",
        "en": "Fight the Landlord"
    },
    {
        "cn": "胜率",
        "tw": "勝率",
        "en": "Win Rate"
    },
    {
        "cn": "游戏场数",
        "tw": "遊戲場數",
        "en": "Number of Games Played"
    },
    {
        "cn": "分数",
        "tw": "分數",
        "en": "Score"
    },
    {
        "cn": "公开",
        "tw": "公開",
        "en": "Public"
    },
    {
        "cn": "账单",
        "tw": "帳單",
        "en": "Bill"
    },
    {
        "cn": "序号",
        "tw": "序號",
        "en": "ID"
    },
    {
        "cn": "类型",
        "tw": "類型",
        "en": "Type"
    },
    {
        "cn": "变化",
        "tw": "變化",
        "en": "Change"
    },
    {
        "cn": "盈余",
        "tw": "盈餘",
        "en": "Surplus"
    },
    {
        "cn": "日期",
        "tw": "日期",
        "en": "Date"
    },
    {
        "cn": "充值",
        "tw": "充值",
        "en": "Recharge"
    },
    {
        "cn": "USDT 余额",
        "tw": "USDT 餘額",
        "en": "USDT Balance"
    },
    {
        "cn": "充值金币",
        "tw": "充值金幣",
        "en": "Recharge Gold Coins"
    },
    {
        "cn": "提现",
        "tw": "提現",
        "en": "Withdraw"
    },
    {
        "cn": "USDT 充值",
        "tw": "USDT 充值",
        "en": "USDT Recharge"
    },
    {
        "cn": "区块链网络",
        "tw": "區塊鏈網絡",
        "en": "Blockchain Network"
    },
    {
        "cn": "充值地址",
        "tw": "充值地址",
        "en": "Recharge Address"
    },
    {
        "cn": "复制",
        "tw": "複製",
        "en": "Copy"
    },
    {
        "cn": "确定",
        "tw": "確定",
        "en": "Confirm"
    },
    {
        "cn": "取消",
        "tw": "取消",
        "en": "Cancel"
    },
    {
        "cn": "我的二维码",
        "tw": "我的二維碼",
        "en": "My QR Code"
    },
    {
        "cn": "用户ID",
        "tw": "用戶ID",
        "en": "User ID"
    },
    {
        "cn": "钱包地址",
        "tw": "錢包地址",
        "en": "Wallet Address"
    },
    {
        "cn": "邀请朋友",
        "tw": "邀請朋友",
        "en": "Invite Friends"
    }
]